swarm/__init__.py
swarm/serialhandler.py
swarm/swarm.py
ftswarm_py-1.2.2.dist-info/LICENSE
ftswarm_py-1.2.2.dist-info/METADATA
ftswarm_py-1.2.2.dist-info/WHEEL
ftswarm_py-1.2.2.dist-info/RECORD
