Metadata-Version: 2.1
Name: ftswarm.py
Version: 1.2.2
Summary: A Python library for the ftSwarm Python API
License: MIT
Author: bergschneider
Author-email: magiclake@gmx.de
Requires-Python: >=3.10,<4.0
Classifier: License :: OSI Approved :: MIT License
Classifier: Programming Language :: Python :: 3
Classifier: Programming Language :: Python :: 3.10
Classifier: Programming Language :: Python :: 3.11
Classifier: Programming Language :: Python :: 3.12
Requires-Dist: pyserial (>=3.5,<4.0)
Project-URL: Documentation, https://bloeckchengrafik.de/ftswarm.py/
